at_common_models/__init__.py
at_common_models/base.py
at_common_models/stock/__init__.py
at_common_models/stock/company_profile.py
at_common_models/stock/entry.py
at_common_models/stock/similarity.py
at_common_models/system/__init__.py
at_common_models/system/cache.py
at_common_models/system/prompt.py
at_common_models/system/workflow.py
at_common_models/user/__init__.py
at_common_models/user/account.py
at_common_models/user/oauth.py
at_common_models/user/subscription.py
at_common_models-0.1.41.dist-info/METADATA
at_common_models-0.1.41.dist-info/WHEEL
at_common_models-0.1.41.dist-info/top_level.txt
at_common_models-0.1.41.dist-info/RECORD
