Metadata-Version: 2.4
Name: at-common-models
Version: 0.1.41
Summary: SQLAlchemy models for stock market data
Author: Rui Chen
Project-URL: Homepage, https://github.com/apex-trader/at-common-models
Project-URL: Bug Tracker, https://github.com/apex-trader/at-common-models/issues
Requires-Python: >=3.11
Requires-Dist: sqlalchemy>=2.0.0
Requires-Dist: typing_extensions>=4.12.2
Requires-Dist: greenlet>=3.1.1
